LICENCE
openscm_zenodo-0.3.1.dist-info/METADATA
openscm_zenodo-0.3.1.dist-info/WHEEL
openscm_zenodo-0.3.1.dist-info/entry_points.txt
openscm_zenodo-0.3.1.dist-info/licenses/LICENCE
openscm_zenodo/__init__.py
openscm_zenodo/cli/__init__.py
openscm_zenodo/cli/app.py
openscm_zenodo/logging.py
openscm_zenodo/py.typed
openscm_zenodo/zenodo.py
openscm_zenodo-0.3.1.dist-info/RECORD
