Metadata-Version: 2.1
Name: openscm-zenodo
Version: 0.3.1
Summary: Command-line tool for uploading to zenodo.
Author-Email: Zebedee Nicholls <zebedee.nicholls@climate-energy-college.org>, Jared Lewis <jared.lewis@climate-energy-college.org>
License: 3-Clause BSD License
Classifier: Development Status :: 4 - Beta
Classifier: Intended Audience :: Developers
Classifier: License :: OSI Approved :: BSD License
Classifier: Operating System :: OS Independent
Classifier: Programming Language :: Python :: 3.9
Classifier: Programming Language :: Python :: 3.10
Classifier: Programming Language :: Python :: 3.11
Requires-Python: >=3.9
Requires-Dist: requests
Requires-Dist: tqdm
Requires-Dist: typer
Requires-Dist: loguru
Requires-Dist: attrs
Provides-Extra: locked
Requires-Dist: attrs==24.2.0; extra == "locked"
Requires-Dist: certifi==2024.8.30; extra == "locked"
Requires-Dist: charset-normalizer==3.3.2; extra == "locked"
Requires-Dist: click==8.1.7; extra == "locked"
Requires-Dist: colorama==0.4.6; extra == "locked"
Requires-Dist: idna==3.10; extra == "locked"
Requires-Dist: loguru==0.7.2; extra == "locked"
Requires-Dist: markdown-it-py==3.0.0; extra == "locked"
Requires-Dist: mdurl==0.1.2; extra == "locked"
Requires-Dist: pygments==2.18.0; extra == "locked"
Requires-Dist: requests==2.32.3; extra == "locked"
Requires-Dist: rich==13.8.1; extra == "locked"
Requires-Dist: shellingham==1.5.4; extra == "locked"
Requires-Dist: tqdm==4.66.5; extra == "locked"
Requires-Dist: typer==0.12.5; extra == "locked"
Requires-Dist: typing-extensions==4.12.2; extra == "locked"
Requires-Dist: urllib3==2.2.3; extra == "locked"
Requires-Dist: win32-setctime==1.1.0; sys_platform == "win32" and extra == "locked"
